README.rst
setup.py
src/yuntongxun_aiorest/__init__.py
src/yuntongxun_aiorest/attrdict.py
src/yuntongxun_aiorest/auth.py
src/yuntongxun_aiorest/error.py
src/yuntongxun_aiorest/ivr.py
src/yuntongxun_aiorest/rest.py
src/yuntongxun_restapi_asyncio.egg-info/PKG-INFO
src/yuntongxun_restapi_asyncio.egg-info/SOURCES.txt
src/yuntongxun_restapi_asyncio.egg-info/dependency_links.txt
src/yuntongxun_restapi_asyncio.egg-info/top_level.txt