Metadata-Version: 1.1
Name: yuntongxun-restapi-asyncio
Version: 0.1
Summary: asyncio python helper library for yuntongxun.com Restful Web API
Home-page: https://github.com/tanbro/yuntongxun-restapi-asyncio
Author: Liu Xue Yan
Author-email: realtanbro@gmail.com
License: GPL
Keywords: yuntongxun
Platform: UNKNOWN
Classifier: Development Status :: 3 - Alpha
Classifier: Intended Audience :: Developers
Classifier: Topic :: Communications :: Telephony
Classifier: License :: OSI Approved :: GNU General Public License (GPL)
Classifier: Programming Language :: Python :: 3
Classifier: Programming Language :: Python :: 3.5
